datacompass/__init__.py
datacompass/main.py
datacompass-0.4.dist-info/LICENSE
datacompass-0.4.dist-info/METADATA
datacompass-0.4.dist-info/WHEEL
datacompass-0.4.dist-info/top_level.txt
datacompass-0.4.dist-info/RECORD
