Metadata-Version: 2.1
Name: datacompass
Version: 0.4
Summary: EDA in 4 lines of Code
Home-page: https://github.com/koushik2299/DataCompass
Author: sai_koushik
Author-email: saikoushik.gsk@gmail.com
Classifier: Programming Language :: Python :: 3
Classifier: License :: OSI Approved :: MIT License
Classifier: Operating System :: OS Independent
Requires-Python: >=3.6
License-File: LICENSE
Requires-Dist: pandas
